.license.c
.license.py
.version.txt
CHANGES.rst
CMakeLists.txt
LICENSE
MANIFEST.in
README.md
README.rst
setup.cfg
setup.py
TiMemory.egg-info/PKG-INFO
TiMemory.egg-info/SOURCES.txt
TiMemory.egg-info/dependency_links.txt
TiMemory.egg-info/not-zip-safe
TiMemory.egg-info/requires.txt
TiMemory.egg-info/top_level.txt
cmake/Modules/BuildSettings.cmake
cmake/Modules/Compilers.cmake
cmake/Modules/Documentation.cmake
cmake/Modules/MacroUtilities.cmake
cmake/Modules/Options.cmake
cmake/Modules/PackageConfigure.cmake
cmake/Modules/Packages.cmake
cmake/Modules/ProjectSettings.cmake
cmake/Modules/Testing.cmake
cmake/Scripts/generator2file.cmake
cmake/Templates/CMakeLists.txt.in
cmake/Templates/CTestCustom.cmake.in
cmake/Templates/Doxyfile.in
cmake/Templates/TiMemoryConfig.cmake.in
cmake/Templates/__init__.py.in
cmake/Templates/compile-test.cc.in
cmake/Templates/cdash/Build.cmake.in
cmake/Templates/cdash/Coverage.cmake.in
cmake/Templates/cdash/Glob.cmake.in
cmake/Templates/cdash/Init.cmake.in
cmake/Templates/cdash/MemCheck.cmake.in
cmake/Templates/cdash/Stages.cmake.in
cmake/Templates/cdash/Submit.cmake.in
cmake/Templates/cdash/Test.cmake.in
examples/CMakeLists.txt
examples/ex-c/CMakeLists.txt
examples/ex-c/test_c_timing.c
examples/ex-cxx/CMakeLists.txt
examples/ex-cxx/test_cxx_timing.cpp
examples/ex-cxx-mpi/CMakeLists.txt
examples/ex-cxx-mpi/test_cxx_mpi_timing.cpp
examples/ex-cxx-overhead/CMakeLists.txt
examples/ex-cxx-overhead/test_cxx_overhead.cpp
examples/ex-cxx-total/CMakeLists.txt
examples/ex-cxx-total/test_cxx_total.cpp
examples/ex4/CMakeLists.txt
examples/ex4/test_timing.cpp
source/CMakeLists.txt
source/auto_timer.cpp
source/base_clock.cpp
source/base_timer.cpp
source/ctimemory.c
source/environment.cpp
source/formatters.cpp
source/manager.cpp
source/signal_detection.cpp
source/timemory.cpp
source/timer.cpp
source/cereal/.travis.yml
source/cereal/CMakeLists.txt
source/cereal/LICENSE
source/cereal/README.md
source/cereal/appveyor.yml
source/cereal/doc/CMakeLists.txt
source/cereal/doc/DoxygenLayout.xml
source/cereal/doc/doxygen.in
source/cereal/doc/footer.html
source/cereal/doc/mainpage.dox
source/cereal/include/cereal/access.hpp
